jamf_pro_sdk/__about__.py
jamf_pro_sdk/__init__.py
jamf_pro_sdk/exceptions.py
jamf_pro_sdk/helpers.py
jamf_pro_sdk/py.typed
jamf_pro_sdk/clients/__init__.py
jamf_pro_sdk/clients/auth.py
jamf_pro_sdk/clients/classic_api.py
jamf_pro_sdk/clients/jcds2.py
jamf_pro_sdk/clients/webhooks.py
jamf_pro_sdk/clients/pro_api/__init__.py
jamf_pro_sdk/clients/pro_api/pagination.py
jamf_pro_sdk/models/__init__.py
jamf_pro_sdk/models/client.py
jamf_pro_sdk/models/classic/__init__.py
jamf_pro_sdk/models/classic/advanced_computer_searches.py
jamf_pro_sdk/models/classic/categories.py
jamf_pro_sdk/models/classic/computer_groups.py
jamf_pro_sdk/models/classic/computers.py
jamf_pro_sdk/models/classic/criteria.py
jamf_pro_sdk/models/classic/network_segments.py
jamf_pro_sdk/models/classic/packages.py
jamf_pro_sdk/models/pro/__init__.py
jamf_pro_sdk/models/pro/api_options.py
jamf_pro_sdk/models/pro/computers.py
jamf_pro_sdk/models/pro/jcds2.py
jamf_pro_sdk/models/pro/mdm.py
jamf_pro_sdk/models/pro/mobile_devices.py
jamf_pro_sdk/models/pro/packages.py
jamf_pro_sdk/models/webhooks/__init__.py
jamf_pro_sdk/models/webhooks/webhooks.py
jamf_pro_sdk-0.8a1.dist-info/licenses/LICENSE
jamf_pro_sdk-0.8a1.dist-info/METADATA
jamf_pro_sdk-0.8a1.dist-info/WHEEL
jamf_pro_sdk-0.8a1.dist-info/top_level.txt
jamf_pro_sdk-0.8a1.dist-info/RECORD
