Metadata-Version: 2.4
Name: jamf-pro-sdk
Version: 0.8a1
Summary: Jamf Pro SDK for Python
License: MIT
Project-URL: Documentation, https://macadmins.github.io/jamf-pro-sdk-python
Project-URL: Source, https://github.com/macadmins/jamf-pro-sdk-python
Project-URL: Changelog, https://github.com/macadmins/jamf-pro-sdk-python/blob/main/CHANGELOG.md
Keywords: jamf,pro,jss,jps
Classifier: Development Status :: 3 - Alpha
Classifier: Intended Audience :: Developers
Classifier: Topic :: Software Development :: Libraries
Classifier: License :: OSI Approved :: MIT No Attribution License (MIT-0)
Classifier: Programming Language :: Python :: 3 :: Only
Classifier: Programming Language :: Python :: 3.9
Classifier: Programming Language :: Python :: 3.10
Classifier: Programming Language :: Python :: 3.11
Classifier: Programming Language :: Python :: 3.12
Requires-Python: <4,>=3.9
License-File: LICENSE
Requires-Dist: requests<3,>=2.28.1
Requires-Dist: pydantic<3,>=2
Requires-Dist: dicttoxml<2,>=1.7.16
Requires-Dist: defusedxml
Provides-Extra: aws
Requires-Dist: boto3<2,>=1.26.45; extra == "aws"
Provides-Extra: macos
Requires-Dist: keyring>=23.13.1; extra == "macos"
Provides-Extra: webhooks
Requires-Dist: polyfactory<3,>=2.1.1; extra == "webhooks"
Provides-Extra: dev
Requires-Dist: boto3<2,>=1.26.45; extra == "dev"
Requires-Dist: keyring>=23.13.1; extra == "dev"
Requires-Dist: polyfactory<3,>=2.1.1; extra == "dev"
Requires-Dist: ruff; extra == "dev"
Requires-Dist: coverage[toml]; extra == "dev"
Requires-Dist: pytest>=6; extra == "dev"
Requires-Dist: pytest-cov; extra == "dev"
Requires-Dist: deepdiff; extra == "dev"
Requires-Dist: sphinx; extra == "dev"
Requires-Dist: autodoc-pydantic; extra == "dev"
Requires-Dist: furo; extra == "dev"
Requires-Dist: build; extra == "dev"
Dynamic: license-file
